<?xml version="1.0" encoding="UTF-8"?>
<beans xmlns="http://www.springframework.org/schema/beans" 
      xmlns:xsi="http://www.w3.org/2001/XMLSchema-instance"
      xmlns:util="http://www.springframework.org/schema/util"  
      xsi:schemaLocation="       
      http://www.springframework.org/schema/beans http://www.springframework.org/schema/beans/spring-beans-3.2.xsd
      http://www.springframework.org/schema/util http://www.springframework.org/schema/util/spring-util-3.2.xsd"      
     default-autowire="byName">
    
    <!-- 全局redisson Bean配置  -->
	<bean id="redisson" class="org.redisson.Redisson" destroy-method="shutdown">
        <constructor-arg index="0">
        <bean class="org.redisson.Config">
        	<constructor-arg index="0">
        		<util:properties location="classpath:redis.properties" />
        	</constructor-arg>
        </bean>
        </constructor-arg>
    </bean>	
	<!-- 全局redis缓存服务-->
	<bean id="cacheableService" class="org.redisson.cache.CacheableService" >
		<property name="redisson">
			<ref bean="redisson"/>
		</property>
	</bean> 
	
    <!-- redisHttpSessionManager -->
	<bean id="redisHttpSessionManager" class="com.heyi.framework.session.RedisHttpSessionManager" >
		<property name="redisson">
			<ref bean="redisson"/>
		</property>
	</bean>
		
	<!-- 启动Spring mvc分发器和所有kafka消费者 -->
	<bean id="springMvcAppInitializer" class="com.heyi.framework.springmvc.SpringMvcMockInitializer" />

</beans>